poppy/__init__.py
poppy/poppy.pypy310-pp73-ppc_64-linux-gnu.so
poppy_py-0.2.1.dist-info/METADATA
poppy_py-0.2.1.dist-info/WHEEL
poppy_py-0.2.1.dist-info/RECORD
