Metadata-Version: 2.4
Name: poppy-py
Version: 0.2.1
Classifier: Programming Language :: Rust
Classifier: Programming Language :: Python :: Implementation :: CPython
Classifier: Programming Language :: Python :: Implementation :: PyPy
Summary: Python bindings for poppy Rust library
Author: quentin.jerome@circl.lu
Author-email: Quentin JEROME <quentin.jerome@circl.lu>
Maintainer-email: Quentin JEROME <quentin.jerome@circl.lu>
License: BSD-3-Clause
Requires-Python: >=3.8
Project-URL: Repository, https://github.com/hashlookup/poppy
